README.md
setup.py
pyvasp/__init__.py
pyvasp/convert.py
pyvasp/files.py
pyvasp/functions.py
pyvasp/job.py
pyvasp/md.py
pyvasp/neb.py
pyvasp/opt.py
pyvasp/pourbaix_diagram.py
pyvasp/pyvasp.py
pyvasp/vasp2boltz.py
pyvasp.egg-info/PKG-INFO
pyvasp.egg-info/SOURCES.txt
pyvasp.egg-info/dependency_links.txt
pyvasp.egg-info/entry_points.txt
pyvasp.egg-info/requires.txt
pyvasp.egg-info/top_level.txt