Metadata-Version: 1.1
Name: pyvasp
Version: 0.0.3
Summary: Multi-option command line tool for VASP
Home-page: https://github.com/ltaiwb/pyvasp
Author: Wenbo Fu
Author-email: ltaiwb@outlook.com
License: MIT
Platform: UNKNOWN
Classifier: Development Status :: 1 - Planning
Classifier: License :: OSI Approved :: MIT License
Classifier: Operating System :: POSIX :: Linux
Classifier: Programming Language :: Python :: 3
Classifier: Topic :: Scientific/Engineering
Classifier: Topic :: Scientific/Engineering :: Chemistry
